<?xml version="1.0" encoding="UTF-8"?><delta><update digester="fnv" path="/3/1/3/6" radius="4" shortened="true"><fingerprint>1310d190;1310d18e;a83be80c;1310d191;ffb1f682;f4d8d3f1;1310d196;027a9443;b40ef5a8</fingerprint><oldvalue>], the temporal resolution and availability of current very high spatial resolution satellite sensors (less than 10 m) are generally not sufficient nor flexible enough for many quantitative remote sensing applications, and they are thus of limited use in detecting and monitoring the dynamics of surficial environmental processes. Recent advances in Earth observation (i.e., EO) are opening new opportunities for environmental monitoring at finer scales [</oldvalue><newvalue>], the temporal resolution and availability of current very high spatial resolution satellite sensors (less than 10 m) nor flexible enough for many quantitative remote sensing applications, and they are thus of limited use in detecting and monitoring the dynamics of surficial environmental processes. Recent advances in Earth observation (i.e., EO) are opening new opportunities for environmental monitoring at finer scales [</newvalue></update></delta>